vgis_gis/__init__.py
vgis_gis/arcgisTools.py
vgis_gis/baiduSetting.py
vgis_gis/coordTools.py
vgis_gis/geocodeTools.py
vgis_gis/geoserverTools.py
vgis_gis/gisTools.py
vgis_gis/poiTools.py
vgis_gis/projTools.py
vgis_gis/qgisTools.py
vgis_gis/shpTools.py
vgis_gis-2.0.1.dist-info/METADATA
vgis_gis-2.0.1.dist-info/WHEEL
vgis_gis-2.0.1.dist-info/top_level.txt
vgis_gis-2.0.1.dist-info/RECORD
